LICENSE
README.md
setup.cfg
setup.py
snowflake_deployer.egg-info/PKG-INFO
snowflake_deployer.egg-info/SOURCES.txt
snowflake_deployer.egg-info/dependency_links.txt
snowflake_deployer.egg-info/entry_points.txt
snowflake_deployer.egg-info/not-zip-safe
snowflake_deployer.egg-info/requires.txt
snowflake_deployer.egg-info/top_level.txt
src/__init__.py
src/cli.py
src/snowflake_classify.py
src/snowflake_deploy.py
src/snowflake_generate_rsa_keys.py
src/snowflake_import.py
src/common/__init__.py
src/common/common.py
src/common/enums.py
src/common/exceptions.py
src/common/processing_vars.py
src/configurator/__init__.py
src/configurator/configurator.py
src/deploy_logger/__init__.py
src/deploy_logger/logger.py
src/deployer/__init__.py
src/deployer/deployer.py
src/deployer/object_types/__init__.py
src/deployer/object_types/deploy_database.py
src/deployer/object_types/deploy_function.py
src/deployer/object_types/deploy_masking_policy.py
src/deployer/object_types/deploy_object.py
src/deployer/object_types/deploy_procedure.py
src/deployer/object_types/deploy_role.py
src/deployer/object_types/deploy_row_access_policy.py
src/deployer/object_types/deploy_schema.py
src/deployer/object_types/deploy_tag.py
src/deployer/object_types/deploy_task.py
src/deployer/object_types/deploy_warehouse.py
src/hasher/__init__.py
src/hasher/hasher.py
src/hasher/object_types/__init__.py
src/hasher/object_types/hash_database.py
src/hasher/object_types/hash_database_all.py
src/hasher/object_types/hash_function.py
src/hasher/object_types/hash_function_all.py
src/hasher/object_types/hash_masking_policy.py
src/hasher/object_types/hash_masking_policy_all.py
src/hasher/object_types/hash_object.py
src/hasher/object_types/hash_object_all.py
src/hasher/object_types/hash_procedure.py
src/hasher/object_types/hash_procedure_all.py
src/hasher/object_types/hash_role.py
src/hasher/object_types/hash_role_all.py
src/hasher/object_types/hash_row_access_policy.py
src/hasher/object_types/hash_row_access_policy_all.py
src/hasher/object_types/hash_schema.py
src/hasher/object_types/hash_schema_all.py
src/hasher/object_types/hash_tag.py
src/hasher/object_types/hash_tag_all.py
src/hasher/object_types/hash_task.py
src/hasher/object_types/hash_task_all.py
src/hasher/object_types/hash_warehouse.py
