Metadata-Version: 2.1
Name: snowflake-deployer
Version: 0.1.21
Summary: Snowflake state based deployer
Author: Justin Hanson, Jernej Plankelj
Project-URL: Project Docs, https://metaopslabs.github.io/snowflake_deployer/
Keywords: SNOWFLAKE,DATAOPS,DEVOPS,DATA,DEPLOYMENT
License-File: LICENSE
